LICENSE.txt
MANIFEST.in
README.md
example.py
requirements.txt
setup.py
stampery.py
stampery.egg-info/PKG-INFO
stampery.egg-info/SOURCES.txt
stampery.egg-info/dependency_links.txt
stampery.egg-info/requires.txt
stampery.egg-info/top_level.txt