Metadata-Version: 1.1
Name: stampery
Version: 0.1.1
Summary: Stampery API for Python
Home-page: https://github.com/stampery/python
Author: Johann Ortiz
Author-email: johann@stampery.com
License: MIT
Keywords: blockchain development
Platform: UNKNOWN
Classifier: Development Status :: 3 - Alpha
Classifier: Intended Audience :: Developers
Classifier: License :: OSI Approved :: MIT License
Classifier: Operating System :: OS Independent
Classifier: Programming Language :: Python :: 2
